8bit_cpu/rtl/alu.v
`timescale 1ns/1ps


module alu(
    input [7:0] a,
    input [7:0] b,
    input [3:0] op,

    output reg [7:0] y,
    output reg carry
);

    always @(*) begin
        y = 8'b00000000;
        carry = 1'b0;
        case (op)
            4'b0000: {carry, y} = a + b; // Addition
            4'b0001: {carry, y} = a - b; // Subtraction
            4'b0010: y = a & b;          // Bitwise AND
            4'b0011: y = a | b;          // Bitwise OR
            4'b0100: y = a ^ b;          // Bitwise XOR
            4'b0101: y = ~(a | b);       // Bitwise NOR
            4'b0110: y = (a > b) ? 8'b00000001 : 8'b00000000; // Greater-than compare 
            4'b0111: y = (a == b) ? 8'b00000001 : 8'b00000000; // Equality compare 
            4'b1000: y = a << 1;         // Shift left by 1
            4'b1001: y = a >> 1;         // Shift right by 1
            default: y = 8'b00000000;
        endcase
    end
endmodule

8bit_cpu/rtl/register.v
`timescale 1ns/1ps

module register(
    input clk,              //clock
    input wen,              //enable
    input [2:0] waddr,      //write (destination) address
    input [2:0] saddr,      //source address
    input [7:0] wdata,      //write data
    output reg [7:0] rdata, //read data (from destination)
    output reg [7:0] sdata  //soure data (from source)
);

    reg [7:0] regs [0:7];   //8 registers (R0 to R7)

    integer i;
    initial begin                   //initalize all registers
        for (i=0; i<8; i=i+1) 
            regs[i] = 0;
    end

    always @(*) begin
        sdata = regs[saddr];
        rdata = regs[waddr];
    end

    always @(posedge clk) begin
        if (wen) 
            regs[waddr] <= wdata;
    end
endmodule

8bit_cpu/rtl/imem.v
`timescale 1ns/1ps

module imem(
        input [7:0] addr,
        output reg [11:0] instr
    );

        reg [11:0] memory [0:255];

        initial begin
            $readmemh("/root/4bit_cpu/program.mem", memory);
        end

        always @(*) begin
            instr = memory[addr];
        end
endmodule

8bit_cpu/rtl/cpu_top.v
`timescale 1ns/1ps

module cpu_top(

    input clk,
    input rst

);
    reg[7:0] pc;        // program counter

    //wires
    wire [11:0] instr;
    wire [3:0] opcode;
    wire [2:0] dest, src;
    wire [7:0] rdata, sdata;
    wire [7:0] alu_result;
    wire wen;
    wire carry;

    //instruction memory
    imem mem (
        .addr(pc),
        .instr(instr)
    );

    //decode instruction field
    assign opcode = instr[11:8];
    assign dest = instr[7:5];
    assign src = instr[4:2];
    assign wen = 1'b1;

    // register file

    register rf(
        .clk(clk),
        .wen(wen),
        .waddr(dest),
        .saddr(src),
        .wdata(alu_result),
        .rdata(rdata),
        .sdata(sdata)
    );

    //alu file

    alu myalu(
        .a(rdata),
        .b(sdata),
        .op(opcode),
        .y(alu_result),
        .carry(carry)
      
    );

    //program counter update
    always @(posedge clk  or posedge rst) begin
        if (rst)
            pc <= 8'd0;
        else
            pc <= pc + 1;
    end

endmodule

8bit_cpu/tb/cpu_tb.v
`timescale 1ns/1ps

module cpu_tb;

    reg clk;
    reg rst;



    //instantiate CPU:
    cpu_top uut(
        .clk(clk),
        .rst(rst)
    );

    //clock generation:
    initial begin
    clk = 0;
        forever begin       
            #5 clk = ~clk; //10ns period
        end
    end

    //reset pulse
    initial begin
        rst = 1;
        #10 rst = 0;          // first release
        #100;
        rst = 1;              // assert reset again
        #10;
        rst = 0;              // release again (restart program)
        #100;
        $finish;
    end
    //Simulation stop:
    initial begin 
        $dumpfile("cpu_tb.vcd");
        $dumpvars(0, cpu_tb);
        #200 $finish; //run 200ns
    end

    reg [7:0] pc_sample;
    always @(posedge clk) begin
        pc_sample <= uut.pc;  // sample synchronously
    end

    reg [2:0] dest_sample;
    reg [2:0] src_sample;
    always @(posedge clk) begin
        dest_sample <= uut.dest;
        src_sample  <= uut.src;
    end

    // monitor CPU signals:
    initial begin
        $display("Time|PC|Instr|Opcode|Dest|Src|Registers R0-R7");
        $monitor("%0t | %0d | %h | %b| %d | %d | %h %h %h %h %h %h %h %h", $time, pc_sample, uut.instr, uut.opcode, dest_sample, src_sample, uut.rf.regs[0], uut.rf.regs[1], uut.rf.regs[2], uut.rf.regs[3], uut.rf.regs[4], uut.rf.regs[5], uut.rf.regs[6], uut.rf.regs[7]);
    end
endmodule

8bit_cpu/cpu_tb.vcd
$version Generated by VerilatedVcd $end
$timescale 1ps $end
 $scope module cpu_tb $end
  $var wire 1 7 clk $end
  $var wire 1 8 rst $end
  $var wire 8 + pc_sample [7:0] $end
  $var wire 3 , dest_sample [2:0] $end
  $var wire 3 - src_sample [2:0] $end
  $scope module uut $end
   $var wire 1 7 clk $end
   $var wire 1 8 rst $end
   $var wire 8 . pc [7:0] $end
   $var wire 12 / instr [11:0] $end
   $var wire 4 0 opcode [3:0] $end
   $var wire 3 1 dest [2:0] $end
   $var wire 3 2 src [2:0] $end
   $var wire 8 3 rdata [7:0] $end
   $var wire 8 4 sdata [7:0] $end
   $var wire 8 5 alu_result [7:0] $end
   $var wire 1 : wen $end
   $var wire 1 6 carry $end
   $scope module mem $end
    $var wire 8 . addr [7:0] $end
    $var wire 12 / instr [11:0] $end
   $upscope $end
   $scope module myalu $end
    $var wire 8 3 a [7:0] $end
    $var wire 8 4 b [7:0] $end
    $var wire 4 0 op [3:0] $end
    $var wire 8 5 y [7:0] $end
    $var wire 1 6 carry $end
   $upscope $end
   $scope module rf $end
    $var wire 1 7 clk $end
    $var wire 1 : wen $end
    $var wire 3 1 waddr [2:0] $end
    $var wire 3 2 saddr [2:0] $end
    $var wire 8 5 wdata [7:0] $end
    $var wire 8 3 rdata [7:0] $end
    $var wire 8 4 sdata [7:0] $end
    $var wire 8 # regs[0] [7:0] $end
    $var wire 8 $ regs[1] [7:0] $end
    $var wire 8 % regs[2] [7:0] $end
    $var wire 8 & regs[3] [7:0] $end
    $var wire 8 ' regs[4] [7:0] $end
    $var wire 8 ( regs[5] [7:0] $end
    $var wire 8 ) regs[6] [7:0] $end
    $var wire 8 * regs[7] [7:0] $end
    $var wire 32 9 i [31:0] $end
   $upscope $end
  $upscope $end
 $upscope $end
$enddefinitions $end


#0
b00000000 #
b00000000 $
b00000000 %
b00000000 &
b00000000 '
b00000000 (
b00000000 )
b00000000 *
b00000000 +
b000 ,
b000 -
b00000000 .
b011101001000 /
b0111 0
b010 1
b010 2
b00000000 3
b00000000 4
b00000001 5
06
07
18
b00000000000000000000000000001000 9
1:
#5000
b00000001 %
b010 ,
b010 -
b00000001 3
b00000001 4
17
#10000
07
08
#15000
b00000001 .
b001100101000 /
b0011 0
b001 1
b00000000 3
17
#20000
07
#25000
b00000001 $
b00000001 +
b001 ,
b00000010 .
b000000001000 /
b0000 0
b000 1
17
#30000
07
#35000
b00000001 #
b00000010 +
b000 ,
b00000011 .
b00000001 3
b00000010 5
17
#40000
07
#45000
b00000010 #
b00000011 +
b00000100 .
b00000010 3
b00000011 5
17
#50000
07
#55000
b00000011 #
b00000100 +
b00000101 .
b010101110000 /
b0101 0
b011 1
b100 2
b00000000 3
b00000000 4
b11111111 5
17
#60000
07
#65000
b11111111 &
b00000101 +
b011 ,
b100 -
b00000110 .
b000110001100 /
b0001 0
b100 1
b011 2
b11111111 4
b00000001 5
16
17
#70000
07
#75000
b00000001 '
b00000110 +
b100 ,
b011 -
b00000111 .
b100001100100 /
b1000 0
b011 1
b001 2
b11111111 3
b00000001 4
b11111110 5
06
17
#80000
07
#85000
b11111110 &
b00000111 +
b011 ,
b001 -
b00001000 .
b11111110 3
b11111100 5
17
#90000
07
#95000
b11111100 &
b00001000 +
b00001001 .
b101000000000 /
b1010 0
b000 1
b000 2
b00000011 3
b00000011 4
b00000000 5
17
#100000
07
#105000
b00000000 #
b00001001 +
b000 ,
b000 -
b00001010 .
b000000000000 /
b0000 0
b00000000 3
b00000000 4
17
#110000
b00000000 .
b011101001000 /
b0111 0
b010 1
b010 2
b00000001 3
b00000001 4
b00000001 5
07
18
#115000
b00000000 +
b010 ,
b010 -
17
#120000
07
08
#125000
b00000001 .
b001100101000 /
b0011 0
b001 1
17
#130000
07
#135000
b00000001 +
b001 ,
b00000010 .
b000000001000 /
b0000 0
b000 1
b00000000 3
17
#140000
07
#145000
b00000001 #
b00000010 +
b000 ,
b00000011 .
b00000001 3
b00000010 5
17
#150000
07
#155000
b00000010 #
b00000011 +
b00000100 .
b00000010 3
b00000011 5
17
#160000
07
#165000
b00000011 #
b00000100 +
b00000101 .
b010101110000 /
b0101 0
b011 1
b100 2
b11111100 3
b00000010 5
17
#170000
07
#175000
b00000010 &
b00000101 +
b011 ,
b100 -
b00000110 .
b000110001100 /
b0001 0
b100 1
b011 2
b00000001 3
b00000010 4
b11111111 5
16
17
#180000
07
#185000
b11111111 '
b00000110 +
b100 ,
b011 -
b00000111 .
b100001100100 /
b1000 0
b011 1
b001 2
b00000010 3
b00000001 4
b00000100 5
06
17
#190000
07
#195000
b00000100 &
b00000111 +
b011 ,
b001 -
b00001000 .
b00000100 3
b00001000 5
17
